semanticache/__init__.py
semanticache/__main__.py
semanticache/cache.py
semanticache/__pycache__/__init__.cpython-311.pyc
semanticache/__pycache__/cache.cpython-311.pyc
semanticache/utils/logger.py
semanticache/utils/run_tests.py
semanticache/utils/__pycache__/logger.cpython-311.pyc
semanticache-0.1.1.dist-info/LICENSE
semanticache-0.1.1.dist-info/METADATA
semanticache-0.1.1.dist-info/WHEEL
semanticache-0.1.1.dist-info/top_level.txt
semanticache-0.1.1.dist-info/RECORD
