Metadata-Version: 2.2
Name: SemantiCache
Version: 0.1.1
Summary: Semantic caching library for LLM apps
Author-email: Abraham Audu <abraham.audu.96@gmail.com>
License: GNU General Public License v3
Project-URL: Homepage, https://github.com/theabrahamaudu/SemantiCache.git
Project-URL: Documentation, https://github.com/theabrahamaudu/SemantiCache/blob/main/docs/SemantiCacheDocs.md
Project-URL: Issues, https://github.com/theabrahamaudu/SemantiCache/issues
Keywords: llm,faiss,semantic,cache,langchain,langchain-community,chatbot
Classifier: Development Status :: 3 - Alpha
Classifier: Intended Audience :: Developers
Classifier: License :: OSI Approved :: GNU General Public License v3 (GPLv3)
Classifier: Programming Language :: Python :: 3
Classifier: Programming Language :: Python :: 3.10
Classifier: Programming Language :: Python :: 3.11
Classifier: Programming Language :: Python :: 3.12
Classifier: Programming Language :: Python :: 3.13
Requires-Python: >=3.10
License-File: LICENSE
Requires-Dist: click
Requires-Dist: pytest
Requires-Dist: pytest_cov
Requires-Dist: Sphinx
Requires-Dist: coverage
Requires-Dist: flake8
Requires-Dist: pyyaml
Requires-Dist: python-ulid==3.0.0
Requires-Dist: langchain==0.1.20
Requires-Dist: langchain-community==0.0.38
Requires-Dist: sentence-transformers==3.3.1
Requires-Dist: faiss-cpu==1.8.0
